ClearList/__init__.py
ClearList/clearList.py
clearList-0.0.4.dist-info/LICENSE
clearList-0.0.4.dist-info/METADATA
clearList-0.0.4.dist-info/WHEEL
clearList-0.0.4.dist-info/top_level.txt
clearList-0.0.4.dist-info/RECORD
