Metadata-Version: 2.1
Name: clearList
Version: 0.0.4
Summary: Customized function pack for lists
Home-page: https://github.com/InterFaze0/clearList
Author: Faruk Ozturk
Author-email: infofaruk9@gmail.com
License: UNKNOWN
Project-URL: Bug Tracker, https://github.com/InterFaze0/clearList
Platform: UNKNOWN
Classifier: Programming Language :: Python :: 3
Classifier: License :: OSI Approved :: MIT License
Classifier: Operating System :: OS Independent
Requires-Python: >=3.6
License-File: LICENSE
